{
  "optimization_timestamp": "2025-09-13T19:14:56.382480",
  "execution_time_seconds": 0.00518345832824707,
  "overall_recommendation": "annual",
  "constraint_limits": {
    "monthly_limit": 0.2,
    "quarterly_limit": 0.4,
    "annual_limit": 1.2
  },
  "feasibility_analysis": {
    "monthly_feasible_strategies": [],
    "quarterly_feasible_strategies": [],
    "annual_feasible_strategies": [
      "HRP",
      "LSTM",
      "GAT",
      "Equal_Weight",
      "Market_Cap"
    ],
    "monthly_feasible_count": 0,
    "quarterly_feasible_count": 0,
    "annual_feasible_count": 5
  },
  "strategy_recommendations": {
    "HRP": "annual",
    "LSTM": "annual",
    "GAT": "annual",
    "Equal_Weight": "annual",
    "Market_Cap": "annual"
  },
  "compliance_improvement": {
    "recommended_frequency": "annual",
    "compliant_strategies": 5,
    "total_strategies": 5,
    "compliance_rate": 1.0,
    "average_turnover": 0.6244962247501812
  },
  "detailed_results": [
    {
      "strategy": "HRP",
      "optimal_frequency": "annual",
      "frequency_results": {
        "monthly": {
          "strategy": "HRP",
          "frequency": "monthly",
          "rebalancing_interval_months": 1,
          "turnover_limit": 0.2,
          "periods_tested": 47,
          "rebalance_events": 47,
          "avg_turnover": 0.64032464498231,
          "max_turnover": 0.6812770516124971,
          "min_turnover": 0.5168556529097577,
          "turnover_volatility": 0.02673109514706408,
          "violations": 47,
          "violation_rate": 1.0,
          "constraint_compliance": false,
          "turnovers": [
            0.5168556529097577,
            0.665749628690316,
            0.6787768207568341,
            0.6468459281979213,
            0.6491970407841477,
            0.6190216863126654,
            0.6352244927773589,
            0.641230058087765,
            0.6523350560670261,
            0.6403537230348664,
            0.6142083632399684,
            0.6225908555002485,
            0.629598051889865,
            0.6337997274344958,
            0.6293725532365932,
            0.6264771609423154,
            0.6517430992978728,
            0.6070367478261118,
            0.654340633365317,
            0.6611267305194692,
            0.600616299460502,
            0.6491787513489801,
            0.6681141700985265,
            0.6358657200118178,
            0.6678055122848164,
            0.6316255160025198,
            0.6492777964362141,
            0.6426194631522452,
            0.6683213932347076,
            0.6090130745686199,
            0.6501321820305139,
            0.6744610542212894,
            0.6812770516124971,
            0.639134392069154,
            0.6393960132571133,
            0.6616072106505486,
            0.6358571253455363,
            0.6290355304697178,
            0.6658538806279981,
            0.6369425564493074,
            0.6331903695324863,
            0.6374228537142416,
            0.6472637116236157,
            0.6644055814687608,
            0.6560801584176702,
            0.5976693151524668,
            0.6472076200557892
          ]
        },
        "quarterly": {
          "strategy": "HRP",
          "frequency": "quarterly",
          "rebalancing_interval_months": 3,
          "turnover_limit": 0.4,
          "periods_tested": 15,
          "rebalance_events": 15,
          "avg_turnover": 0.6358486038754939,
          "max_turnover": 0.6921069863833551,
          "min_turnover": 0.5332245627021728,
          "turnover_volatility": 0.03484429780374671,
          "violations": 15,
          "violation_rate": 1.0,
          "constraint_compliance": false,
          "turnovers": [
            0.5332245627021728,
            0.6485980557981772,
            0.6306549578419138,
            0.6522994180855557,
            0.6432546092875675,
            0.6362828419571518,
            0.6117739463004056,
            0.6921069863833551,
            0.6744895087622126,
            0.6498186363576506,
            0.6411929768903634,
            0.6641859800505501,
            0.6205848713089892,
            0.6280432122514372,
            0.6112184941549046
          ]
        },
        "annual": {
          "strategy": "HRP",
          "frequency": "annual",
          "rebalancing_interval_months": 12,
          "turnover_limit": 1.2,
          "periods_tested": 3,
          "rebalance_events": 3,
          "avg_turnover": 0.6056397783581965,
          "max_turnover": 0.6621604767676024,
          "min_turnover": 0.523592880705539,
          "turnover_volatility": 0.059379765383276405,
          "violations": 0,
          "violation_rate": 0.0,
          "constraint_compliance": true,
          "turnovers": [
            0.523592880705539,
            0.6311659776014482,
            0.6621604767676024
          ]
        }
      },
      "performance_summary": {
        "monthly_feasible": false,
        "quarterly_feasible": false,
        "annual_feasible": true,
        "optimal_avg_turnover": 0.6056397783581965,
        "optimal_violation_rate": 0.0
      }
    },
    {
      "strategy": "LSTM",
      "optimal_frequency": "annual",
      "frequency_results": {
        "monthly": {
          "strategy": "LSTM",
          "frequency": "monthly",
          "rebalancing_interval_months": 1,
          "turnover_limit": 0.2,
          "periods_tested": 47,
          "rebalance_events": 47,
          "avg_turnover": 0.6423550913614836,
          "max_turnover": 0.6958968339242484,
          "min_turnover": 0.5023419466048878,
          "turnover_volatility": 0.02988272491675822,
          "violations": 47,
          "violation_rate": 1.0,
          "constraint_compliance": false,
          "turnovers": [
            0.5023419466048878,
            0.6493975531838911,
            0.634347055195838,
            0.6115145952001405,
            0.6528031819814796,
            0.6205888685386838,
            0.6770253781294198,
            0.6224093281782259,
            0.6123994926078066,
            0.6534054130748039,
            0.6842954303024109,
            0.6564918309857083,
            0.6516628121888951,
            0.6534700610795922,
            0.6763000030436436,
            0.6710185329696697,
            0.6370342790203082,
            0.6259049448110002,
            0.6958968339242484,
            0.6561562605526357,
            0.6443196857323521,
            0.6285385117618392,
            0.6576567947824286,
            0.6253365626610661,
            0.6045402625552956,
            0.6396558544225104,
            0.6209097693881558,
            0.6231481036662248,
            0.6214917446422209,
            0.6371785453437632,
            0.6634674603939454,
            0.6487962370227003,
            0.6583887205569545,
            0.6682910813170305,
            0.6676704922090599,
            0.6434430160167194,
            0.6772143799184828,
            0.6286883554612144,
            0.6628053489084669,
            0.6465486527131028,
            0.6572965709424372,
            0.6616933834711687,
            0.6297476938045898,
            0.6691119452848546,
            0.6105691087819993,
            0.6158575059760301,
            0.63385970468183
          ]
        },
        "quarterly": {
          "strategy": "LSTM",
          "frequency": "quarterly",
          "rebalancing_interval_months": 3,
          "turnover_limit": 0.4,
          "periods_tested": 15,
          "rebalance_events": 15,
          "avg_turnover": 0.6441753173220218,
          "max_turnover": 0.6908184022681167,
          "min_turnover": 0.542688569236015,
          "turnover_volatility": 0.03471721590168861,
          "violations": 15,
          "violation_rate": 1.0,
          "constraint_compliance": false,
          "turnovers": [
            0.542688569236015,
            0.6596660320374801,
            0.6679993345717682,
            0.6522776291984893,
            0.6908184022681167,
            0.6683447288457057,
            0.6265031964958102,
            0.6330259451584562,
            0.660310930781358,
            0.6708375871465952,
            0.6595909626198562,
            0.6631149745955481,
            0.6323888726432301,
            0.6346172151241648,
            0.6004453791077338
          ]
        },
        "annual": {
          "strategy": "LSTM",
          "frequency": "annual",
          "rebalancing_interval_months": 12,
          "turnover_limit": 1.2,
          "periods_tested": 3,
          "rebalance_events": 3,
          "avg_turnover": 0.6419937405817765,
          "max_turnover": 0.7145939469040756,
          "min_turnover": 0.5347253469605531,
          "turnover_volatility": 0.07741485955274012,
          "violations": 0,
          "violation_rate": 0.0,
          "constraint_compliance": true,
          "turnovers": [
            0.5347253469605531,
            0.7145939469040756,
            0.6766619278807009
          ]
        }
      },
      "performance_summary": {
        "monthly_feasible": false,
        "quarterly_feasible": false,
        "annual_feasible": true,
        "optimal_avg_turnover": 0.6419937405817765,
        "optimal_violation_rate": 0.0
      }
    },
    {
      "strategy": "GAT",
      "optimal_frequency": "annual",
      "frequency_results": {
        "monthly": {
          "strategy": "GAT",
          "frequency": "monthly",
          "rebalancing_interval_months": 1,
          "turnover_limit": 0.2,
          "periods_tested": 47,
          "rebalance_events": 47,
          "avg_turnover": 0.64032464498231,
          "max_turnover": 0.6812770516124971,
          "min_turnover": 0.5168556529097575,
          "turnover_volatility": 0.026731095147064083,
          "violations": 47,
          "violation_rate": 1.0,
          "constraint_compliance": false,
          "turnovers": [
            0.5168556529097575,
            0.665749628690316,
            0.6787768207568341,
            0.6468459281979213,
            0.6491970407841477,
            0.6190216863126656,
            0.6352244927773589,
            0.641230058087765,
            0.652335056067026,
            0.6403537230348662,
            0.6142083632399682,
            0.6225908555002484,
            0.6295980518898648,
            0.6337997274344956,
            0.6293725532365932,
            0.6264771609423154,
            0.6517430992978728,
            0.6070367478261118,
            0.6543406333653169,
            0.6611267305194692,
            0.6006162994605021,
            0.6491787513489802,
            0.6681141700985265,
            0.6358657200118181,
            0.6678055122848164,
            0.6316255160025197,
            0.6492777964362141,
            0.6426194631522452,
            0.6683213932347076,
            0.60901307456862,
            0.650132182030514,
            0.6744610542212894,
            0.6812770516124971,
            0.639134392069154,
            0.6393960132571133,
            0.6616072106505486,
            0.6358571253455363,
            0.6290355304697178,
            0.6658538806279981,
            0.6369425564493074,
            0.6331903695324864,
            0.6374228537142417,
            0.647263711623616,
            0.6644055814687609,
            0.6560801584176702,
            0.597669315152467,
            0.6472076200557892
          ]
        },
        "quarterly": {
          "strategy": "GAT",
          "frequency": "quarterly",
          "rebalancing_interval_months": 3,
          "turnover_limit": 0.4,
          "periods_tested": 15,
          "rebalance_events": 15,
          "avg_turnover": 0.6358486038754939,
          "max_turnover": 0.6921069863833551,
          "min_turnover": 0.5332245627021728,
          "turnover_volatility": 0.03484429780374672,
          "violations": 15,
          "violation_rate": 1.0,
          "constraint_compliance": false,
          "turnovers": [
            0.5332245627021728,
            0.6485980557981774,
            0.6306549578419138,
            0.6522994180855557,
            0.6432546092875675,
            0.6362828419571518,
            0.6117739463004055,
            0.6921069863833551,
            0.6744895087622126,
            0.6498186363576506,
            0.6411929768903634,
            0.6641859800505501,
            0.6205848713089893,
            0.6280432122514372,
            0.6112184941549046
          ]
        },
        "annual": {
          "strategy": "GAT",
          "frequency": "annual",
          "rebalancing_interval_months": 12,
          "turnover_limit": 1.2,
          "periods_tested": 3,
          "rebalance_events": 3,
          "avg_turnover": 0.6056397783581965,
          "max_turnover": 0.6621604767676026,
          "min_turnover": 0.5235928807055389,
          "turnover_volatility": 0.05937976538327653,
          "violations": 0,
          "violation_rate": 0.0,
          "constraint_compliance": true,
          "turnovers": [
            0.5235928807055389,
            0.6311659776014482,
            0.6621604767676026
          ]
        }
      },
      "performance_summary": {
        "monthly_feasible": false,
        "quarterly_feasible": false,
        "annual_feasible": true,
        "optimal_avg_turnover": 0.6056397783581965,
        "optimal_violation_rate": 0.0
      }
    },
    {
      "strategy": "Equal_Weight",
      "optimal_frequency": "annual",
      "frequency_results": {
        "monthly": {
          "strategy": "Equal_Weight",
          "frequency": "monthly",
          "rebalancing_interval_months": 1,
          "turnover_limit": 0.2,
          "periods_tested": 47,
          "rebalance_events": 47,
          "avg_turnover": 0.647409209298668,
          "max_turnover": 0.7120471833516996,
          "min_turnover": 0.5104963214134429,
          "turnover_volatility": 0.03180331131624305,
          "violations": 47,
          "violation_rate": 1.0,
          "constraint_compliance": false,
          "turnovers": [
            0.5104963214134429,
            0.6517206652401897,
            0.6141946861610277,
            0.691231582357928,
            0.6521398286452164,
            0.6110078597679873,
            0.6577073222164163,
            0.6711301510298081,
            0.6700396395419705,
            0.6274539054871262,
            0.6480556949678071,
            0.655640301655279,
            0.6366726883266429,
            0.6570118423148065,
            0.6984390748834237,
            0.6958684450026548,
            0.6767990666360274,
            0.6202180471238637,
            0.6602119503766861,
            0.6440276112301544,
            0.6358620793947733,
            0.6403497543713678,
            0.662853753358625,
            0.6681087398327152,
            0.6455407820864949,
            0.6373240586895936,
            0.6513466207861975,
            0.6422927787371604,
            0.640021730504656,
            0.6509049372398508,
            0.6736335825895303,
            0.6892326816118699,
            0.6048093619201143,
            0.6024979797886387,
            0.7120471833516996,
            0.644862395123738,
            0.6455840267712072,
            0.6603244835903905,
            0.629874972973852,
            0.6357435824263127,
            0.6714466186869636,
            0.6383105708273167,
            0.6592016166539839,
            0.6270997996327152,
            0.6048973262104581,
            0.6696837378916507,
            0.6343109976070586
          ]
        },
        "quarterly": {
          "strategy": "Equal_Weight",
          "frequency": "quarterly",
          "rebalancing_interval_months": 3,
          "turnover_limit": 0.4,
          "periods_tested": 15,
          "rebalance_events": 15,
          "avg_turnover": 0.6516491956912527,
          "max_turnover": 0.7118435036824605,
          "min_turnover": 0.5209186260176497,
          "turnover_volatility": 0.04334708106538159,
          "violations": 15,
          "violation_rate": 1.0,
          "constraint_compliance": false,
          "turnovers": [
            0.5209186260176497,
            0.7118435036824605,
            0.6861564228939666,
            0.6701086874537089,
            0.6391548145436605,
            0.6831378216589703,
            0.6479545584573001,
            0.6314090319351746,
            0.6519262209561614,
            0.6852056079071559,
            0.6500946381281981,
            0.655329194416008,
            0.6250602461967069,
            0.6233418316987382,
            0.6930967294229311
          ]
        },
        "annual": {
          "strategy": "Equal_Weight",
          "frequency": "annual",
          "rebalancing_interval_months": 12,
          "turnover_limit": 1.2,
          "periods_tested": 3,
          "rebalance_events": 3,
          "avg_turnover": 0.5986015461864042,
          "max_turnover": 0.6378085787813107,
          "min_turnover": 0.5469888787968473,
          "turnover_volatility": 0.038100562614486966,
          "violations": 0,
          "violation_rate": 0.0,
          "constraint_compliance": true,
          "turnovers": [
            0.5469888787968473,
            0.6378085787813107,
            0.6110071809810544
          ]
        }
      },
      "performance_summary": {
        "monthly_feasible": false,
        "quarterly_feasible": false,
        "annual_feasible": true,
        "optimal_avg_turnover": 0.5986015461864042,
        "optimal_violation_rate": 0.0
      }
    },
    {
      "strategy": "Market_Cap",
      "optimal_frequency": "annual",
      "frequency_results": {
        "monthly": {
          "strategy": "Market_Cap",
          "frequency": "monthly",
          "rebalancing_interval_months": 1,
          "turnover_limit": 0.2,
          "periods_tested": 47,
          "rebalance_events": 47,
          "avg_turnover": 0.6838919316653175,
          "max_turnover": 0.7435344275279901,
          "min_turnover": 0.5332783443992235,
          "turnover_volatility": 0.03472677983831997,
          "violations": 47,
          "violation_rate": 1.0,
          "constraint_compliance": false,
          "turnovers": [
            0.5332783443992235,
            0.6857395730876354,
            0.6630900176651973,
            0.6595555257089172,
            0.7056694353137738,
            0.643442518068119,
            0.7143469403603496,
            0.6570405245898543,
            0.6463583151397414,
            0.682557649415134,
            0.7089081158829964,
            0.6867304390343976,
            0.660900233767143,
            0.6790429804221971,
            0.7184116603800459,
            0.7091685827798953,
            0.687276511273639,
            0.6889273825488056,
            0.7435344275279901,
            0.7114159714758876,
            0.6949100991709448,
            0.6695782344072507,
            0.6987396733799627,
            0.6619831840857049,
            0.6448684858766054,
            0.6830245501069947,
            0.6520491733243531,
            0.6622786254469001,
            0.6589903619215832,
            0.684704607417021,
            0.7327639274432718,
            0.7316650161500909,
            0.7262564886946585,
            0.7119961959282786,
            0.7047253288057207,
            0.7114155250272929,
            0.723361263689321,
            0.6577896653610362,
            0.6873594555969752,
            0.6859680887356552,
            0.7080339367880941,
            0.7153426687542237,
            0.6827513262051124,
            0.6998072397227131,
            0.6588193918294275,
            0.6335223761938709,
            0.6748207493659136
          ]
        },
        "quarterly": {
          "strategy": "Market_Cap",
          "frequency": "quarterly",
          "rebalancing_interval_months": 3,
          "turnover_limit": 0.4,
          "periods_tested": 15,
          "rebalance_events": 15,
          "avg_turnover": 0.6821961802462478,
          "max_turnover": 0.7222337731825246,
          "min_turnover": 0.563432274202689,
          "turnover_volatility": 0.03773028451044348,
          "violations": 15,
          "violation_rate": 1.0,
          "constraint_compliance": false,
          "turnovers": [
            0.563432274202689,
            0.6929729673417825,
            0.6914082383385359,
            0.6736563080998781,
            0.7184155260787946,
            0.7194511574312662,
            0.6877982049275612,
            0.6796253942148316,
            0.6736640167693213,
            0.7027609681495899,
            0.7057581199625567,
            0.7222337731825246,
            0.6811512974963403,
            0.6779683058474757,
            0.6426461516505703
          ]
        },
        "annual": {
          "strategy": "Market_Cap",
          "frequency": "annual",
          "rebalancing_interval_months": 12,
          "turnover_limit": 1.2,
          "periods_tested": 3,
          "rebalance_events": 3,
          "avg_turnover": 0.6706062802663327,
          "max_turnover": 0.7381205126643482,
          "min_turnover": 0.5549559954814337,
          "turnover_volatility": 0.08215886944717596,
          "violations": 0,
          "violation_rate": 0.0,
          "constraint_compliance": true,
          "turnovers": [
            0.5549559954814337,
            0.7381205126643482,
            0.7187423326532165
          ]
        }
      },
      "performance_summary": {
        "monthly_feasible": false,
        "quarterly_feasible": false,
        "annual_feasible": true,
        "optimal_avg_turnover": 0.6706062802663327,
        "optimal_violation_rate": 0.0
      }
    }
  ]
}